ergate/__init__.py
ergate/__version__.py
ergate/annotations.py
ergate/app.py
ergate/depends_cache.py
ergate/exceptions.py
ergate/inspect.py
ergate/interrupt.py
ergate/job.py
ergate/job_runner.py
ergate/job_status.py
ergate/log.py
ergate/paths.py
ergate/py.typed
ergate/queue.py
ergate/state_store.py
ergate/types.py
ergate/workflow.py
ergate/workflow_registry.py
ergate/workflow_step.py
ergate/signals/__init__.py
ergate/signals/enum.py
ergate/signals/handler.py
ergate-0.6.0.dist-info/licenses/LICENSE
ergate-0.6.0.dist-info/METADATA
ergate-0.6.0.dist-info/WHEEL
ergate-0.6.0.dist-info/entry_points.txt
ergate-0.6.0.dist-info/top_level.txt
ergate-0.6.0.dist-info/RECORD
