Metadata-Version: 2.4
Name: ergate
Version: 0.6.0
Summary: Workflows made easy, your way
Author: prryplatypus
License: MIT License
Project-URL: Repository, https://github.com/prryplatypus/ergate
Keywords: workflow,worker
Classifier: Development Status :: 3 - Alpha
Classifier: Intended Audience :: Developers
Classifier: Intended Audience :: Information Technology
Classifier: Intended Audience :: System Administrators
Classifier: License :: OSI Approved :: MIT License
Classifier: Operating System :: OS Independent
Classifier: Programming Language :: Python :: 3
Classifier: Programming Language :: Python
Classifier: Topic :: Software Development
Classifier: Topic :: Software Development :: Libraries
Classifier: Topic :: Software Development :: Libraries :: Application Frameworks
Classifier: Topic :: Software Development :: Libraries :: Python Modules
Requires-Python: >=3.10
License-File: LICENSE
Requires-Dist: pydantic>=2.0.0
Provides-Extra: docs
Requires-Dist: mkdocs-material; extra == "docs"
Provides-Extra: test
Requires-Dist: mypy; extra == "test"
Requires-Dist: ruff; extra == "test"
Requires-Dist: flake8; extra == "test"
Requires-Dist: flake8-pyproject; extra == "test"
Dynamic: license-file
